{
  "document_id": "table_caption_reference",
  "required_docling_kinds": [
    "title",
    "section_header",
    "text",
    "picture",
    "table",
    "formula",
    "caption",
    "list",
    "footnote"
  ],
  "body_order_constraints": [
    "paragraph",
    "title",
    "paragraph",
    "section",
    "table",
    "paragraph",
    "caption",
    "paragraph",
    "paragraph",
    "reference",
    "paragraph"
  ],
  "required_caption_relations": [
    {
      "type": "caption_of",
      "caption_text": "Sample table",
      "source_block_id": "gt:table_caption_reference:b0007",
      "target_label": null
    }
  ],
  "required_reference_sidecar_entries": [
    "tab:s"
  ],
  "expected_markdown_snippets": [
    "Table Caption Reference"
  ],
  "allowed_degradation_warnings": [],
  "tolerance_policy": {
    "whitespace": true
  }
}