{
  "command": [
    "mineru",
    "-p",
    "/home/jgarcia/pdf2md/pdf2md_old/.current/latex_docling_groundtruth/batch_001/all_features_small/input/all_features_small.pdf",
    "-o",
    "/home/jgarcia/pdf2md/pdf2md_old/.current/latex_docling_groundtruth/batch_001/all_features_small/backend_ir/mineru/.current/extraction_ir/all_features_small/official_results",
    "-b",
    "pipeline",
    "-m",
    "auto",
    "-l",
    "en",
    "-f",
    "true",
    "-t",
    "true"
  ],
  "started_at": "2026-05-03T18:48:01.174421Z",
  "ended_at": "2026-05-03T18:48:28.166714Z",
  "returncode": 0,
  "stdout": "Start MinerU FastAPI Service: http://127.0.0.1:39821\nAPI documentation: http://127.0.0.1:39821/docs\n",
  "stderr": "2026-05-03 20:48:02.826 | INFO     | mineru.cli.client:run_orchestrated_cli:874 - Started local mineru-api at http://127.0.0.1:39821\n2026-05-03 20:48:04.569 | INFO     | __main__:create_app:260 - Request concurrency limited to 3\nINFO:     Started server process [1018715]\nINFO:     Waiting for application startup.\nINFO:     Application startup complete.\nINFO:     Uvicorn running on http://127.0.0.1:39821 (Press CTRL+C to quit)\n2026-05-03 20:48:04.837 | INFO     | mineru.cli.client:run_planned_task:771 - Submitting batch 1/1 | 1 document, 1 page in this batch | 1 page total | task#1 [all_features_small]\n2026-05-03 20:48:07.047 | INFO     | mineru.backend.pipeline.pipeline_analyze:doc_analyze_streaming:183 - Pipeline processing-window multi-file run. doc_count=1, total_pages=1, window_size=64, total_batches=1\n2026-05-03 20:48:08.834 | INFO     | mineru.backend.pipeline.pipeline_analyze:doc_analyze_streaming:235 - Pipeline processing window batch 1/1: 1/1 pages, batch_pages=1, doc_slices=doc0:1-1\n2026-05-03 20:48:09.240 | INFO     | mineru.backend.pipeline.pipeline_analyze:batch_image_analyze:328 - GPU Memory: 47 GB, Batch Ratio: 16. \n2026-05-03 20:48:09.240 | INFO     | mineru.backend.pipeline.model_init:__init__:207 - DocAnalysis init, this may take some times......\n\nFetching 7 files:   0%|          | 0/7 [00:00<?, ?it/s]\nFetching 7 files: 100%|██████████| 7/7 [00:00<00:00, 54981.51it/s]\n\nFetching 3 files:   0%|          | 0/3 [00:00<?, ?it/s]\nFetching 3 files: 100%|██████████| 3/3 [00:00<00:00, 8786.95it/s]\n\nFetching 1 files:   0%|          | 0/1 [00:00<?, ?it/s]\nFetching 1 files: 100%|██████████| 1/1 [00:00<00:00, 3141.80it/s]\n\nFetching 1 files:   0%|          | 0/1 [00:00<?, ?it/s]\nFetching 1 files: 100%|██████████| 1/1 [00:00<00:00, 7025.63it/s]\n\nFetching 1 files:   0%|          | 0/1 [00:00<?, ?it/s]\nFetching 1 files: 100%|██████████| 1/1 [00:00<00:00, 3037.15it/s]\n\nFetching 1 files:   0%|          | 0/1 [00:00<?, ?it/s]\nFetching 1 files: 100%|██████████| 1/1 [00:00<00:00, 4401.16it/s]\n\nFetching 1 files:   0%|          | 0/1 [00:00<?, ?it/s]\nFetching 1 files: 100%|██████████| 1/1 [00:00<00:00, 3310.42it/s]\n\nFetching 1 files:   0%|          | 0/1 [00:00<?, ?it/s]\nFetching 1 files: 100%|██████████| 1/1 [00:00<00:00, 7958.83it/s]\n\nFetching 1 files:   0%|          | 0/1 [00:00<?, ?it/s]\nFetching 1 files: 100%|██████████| 1/1 [00:00<00:00, 3426.72it/s]\n\nFetching 1 files:   0%|          | 0/1 [00:00<?, ?it/s]\nFetching 1 files: 100%|██████████| 1/1 [00:00<00:00, 9020.01it/s]\n\nFetching 1 files:   0%|          | 0/1 [00:00<?, ?it/s]\nFetching 1 files: 100%|██████████| 1/1 [00:00<00:00, 2219.21it/s]\n\nFetching 1 files:   0%|          | 0/1 [00:00<?, ?it/s]\nFetching 1 files: 100%|██████████| 1/1 [00:00<00:00, 2608.40it/s]\n2026-05-03 20:48:14.321 | INFO     | mineru.backend.pipeline.model_init:__init__:260 - DocAnalysis init done!\n2026-05-03 20:48:14.321 | INFO     | mineru.backend.pipeline.pipeline_analyze:custom_model_init:83 - model init cost: 5.080362319946289\n\nLayout Predict:   0%|          | 0/1 [00:00<?, ?it/s]\nLayout Predict: 100%|██████████| 1/1 [00:00<00:00,  2.24it/s]\nLayout Predict: 100%|██████████| 1/1 [00:00<00:00,  2.24it/s]\n\nMFR Predict:   0%|          | 0/1 [00:00<?, ?it/s]\nMFR Predict: 100%|██████████| 1/1 [00:00<00:00,  4.01it/s]\nMFR Predict: 100%|██████████| 1/1 [00:00<00:00,  4.01it/s]\n\nTable-ocr det: 0it [00:00, ?it/s]\nTable-ocr det: 0it [00:00, ?it/s]\n\nTable-wireless Predict: 0it [00:00, ?it/s]\nTable-wireless Predict: 0it [00:00, ?it/s]\n\nFetching 1 files:   0%|          | 0/1 [00:00<?, ?it/s]\nFetching 1 files: 100%|██████████| 1/1 [00:00<00:00, 2061.08it/s]\n\nFetching 1 files:   0%|          | 0/1 [00:00<?, ?it/s]\nFetching 1 files: 100%|██████████| 1/1 [00:00<00:00, 5370.43it/s]\n\nOCR-det en:   0%|          | 0/7 [00:00<?, ?it/s]\nOCR-det en:  71%|███████▏  | 5/7 [00:00<00:00, 46.54it/s]\nOCR-det en: 100%|██████████| 7/7 [00:00<00:00, 55.53it/s]\n\nSeal Predict: 0it [00:00, ?it/s]\nSeal Predict: 0it [00:00, ?it/s]\n\nProcessing pages:   0%|          | 0/1 [00:00<?, ?it/s]\nProcessing pages: 100%|██████████| 1/1 [00:00<00:00, 32.80it/s]\n2026-05-03 20:48:16.420 | INFO     | mineru.cli.client:run_planned_task:807 - Completed batch 1/1 | Processed 1/1 page | 1 of 1 batch finished | task#1 [all_features_small]\nINFO:     Shutting down\nINFO:     Waiting for application shutdown.\nINFO:     Application shutdown complete.\nINFO:     Finished server process [1018715]\n"
}
