{
  "document_id": "two_figures_cross_references",
  "expected_title": "Two Figures Cross References",
  "expected_sections": [
    "Visuals"
  ],
  "expected_subsections": [],
  "expected_ordered_block_constraints": [
    "paragraph",
    "title",
    "paragraph",
    "section",
    "figure",
    "paragraph",
    "caption",
    "figure",
    "paragraph",
    "caption",
    "paragraph",
    "reference",
    "paragraph",
    "reference",
    "paragraph"
  ],
  "expected_labels": [
    "fig:one",
    "fig:two"
  ],
  "expected_references": [
    {
      "id": "gt:ref:two_figures_cross_references:0",
      "source_node_id": "gt:two_figures_cross_references:b0012",
      "source_block_id": "gt:two_figures_cross_references:b0012",
      "target_label": "fig:one",
      "relation_type": "reference_to",
      "reference_text": "\\ref{fig:one}",
      "target_block_id": "gt:two_figures_cross_references:b0005",
      "target_node_id": "gt:two_figures_cross_references:b0005",
      "resolved": true,
      "expected_resolved": true
    },
    {
      "id": "gt:ref:two_figures_cross_references:1",
      "source_node_id": "gt:two_figures_cross_references:b0014",
      "source_block_id": "gt:two_figures_cross_references:b0014",
      "target_label": "fig:two",
      "relation_type": "reference_to",
      "reference_text": "\\ref{fig:two}",
      "target_block_id": "gt:two_figures_cross_references:b0008",
      "target_node_id": "gt:two_figures_cross_references:b0008",
      "resolved": true,
      "expected_resolved": true
    }
  ],
  "expected_captions": [
    {
      "type": "caption_of",
      "caption_text": "First",
      "source_block_id": "gt:two_figures_cross_references:b0007",
      "target_label": null
    },
    {
      "type": "caption_of",
      "caption_text": "Second",
      "source_block_id": "gt:two_figures_cross_references:b0010",
      "target_label": null
    }
  ],
  "expected_nested_list_structure": true,
  "expected_table_cells": [],
  "expected_markdown_snippets": [
    "Two Figures Cross References"
  ],
  "allowed_warnings": [],
  "tolerance_policy": {
    "whitespace": true
  }
}